spelunk/__init__.py
spelunk/spelunk.py
spelunk-0.1.6.dist-info/LICENSE
spelunk-0.1.6.dist-info/WHEEL
spelunk-0.1.6.dist-info/METADATA
spelunk-0.1.6.dist-info/RECORD
