Metadata-Version: 2.1
Name: spelunk
Version: 0.1.6
Summary: Package with helpful object recursion utils
Home-page: https://github.com/tomarken/spelunk
License: MIT
Author: Spencer Tomarken
Author-email: stomarken@gmail.com
Requires-Python: >=3.9,<3.10
Classifier: License :: OSI Approved :: MIT License
Classifier: Programming Language :: Python :: 3
Classifier: Programming Language :: Python :: 3.9
Project-URL: Repository, https://github.com/tomarken/spelunk
